litestar_oauth/__init__.py
litestar_oauth/__metadata__.py
litestar_oauth/base.py
litestar_oauth/contrib/litestar/__init__.py
litestar_oauth/contrib/litestar/config.py
litestar_oauth/contrib/litestar/controllers.py
litestar_oauth/contrib/litestar/dependencies.py
litestar_oauth/contrib/litestar/guards.py
litestar_oauth/contrib/litestar/plugin.py
litestar_oauth/exceptions.py
litestar_oauth/providers/__init__.py
litestar_oauth/providers/bitbucket.py
litestar_oauth/providers/discord.py
litestar_oauth/providers/facebook.py
litestar_oauth/providers/generic.py
litestar_oauth/providers/github.py
litestar_oauth/providers/gitlab.py
litestar_oauth/providers/google.py
litestar_oauth/providers/linkedin.py
litestar_oauth/providers/microsoft.py
litestar_oauth/providers/twitter.py
litestar_oauth/service.py
litestar_oauth/testing/__init__.py
litestar_oauth/testing/fixtures.py
litestar_oauth/testing/mocks.py
litestar_oauth/types.py
litestar_oauth-0.1.0.dist-info/WHEEL
litestar_oauth-0.1.0.dist-info/METADATA
litestar_oauth-0.1.0.dist-info/RECORD
