Metadata-Version: 2.3
Name: litestar-oauth
Version: 0.1.0
Summary: OAuth2 authentication plugin for Litestar
Keywords: oauth,oauth2,authentication,litestar,async,oidc
Author: Jacob Coffee
Author-email: Jacob Coffee <jacob@z7x.org>
License: MIT
Classifier: Development Status :: 3 - Alpha
Classifier: Environment :: Web Environment
Classifier: Intended Audience :: Developers
Classifier: License :: OSI Approved :: MIT License
Classifier: Operating System :: OS Independent
Classifier: Programming Language :: Python
Classifier: Programming Language :: Python :: 3.10
Classifier: Programming Language :: Python :: 3.11
Classifier: Programming Language :: Python :: 3.12
Classifier: Programming Language :: Python :: 3.13
Classifier: Programming Language :: Python :: 3 :: Only
Classifier: Topic :: Internet :: WWW/HTTP :: Session
Classifier: Topic :: Security
Classifier: Typing :: Typed
Requires-Dist: httpx>=0.27.0
Requires-Dist: litestar>=2.0.0
Requires-Dist: aiohttp>=3.9.0 ; extra == 'aiohttp'
Requires-Dist: pyjwt>=2.8.0 ; extra == 'all'
Requires-Dist: cryptography>=41.0.0 ; extra == 'all'
Requires-Dist: pyjwt>=2.8.0 ; extra == 'apple'
Requires-Dist: cryptography>=41.0.0 ; extra == 'apple'
Requires-Dist: msal>=1.26.0 ; extra == 'microsoft'
Requires-Python: >=3.10
Project-URL: Changelog, https://github.com/JacobCoffee/litestar-oauth/releases/
Project-URL: Discord, https://discord.gg/litestar-919193495116337154
Project-URL: Documentation, https://jacobcoffee.github.io/litestar-oauth
Project-URL: Issue Tracker, https://github.com/JacobCoffee/litestar-oauth/issues
Project-URL: Repository, https://github.com/JacobCoffee/litestar-oauth
Provides-Extra: aiohttp
Provides-Extra: all
Provides-Extra: apple
Provides-Extra: microsoft
Provides-Extra: standard
